unipacker/__init__.py
unipacker/apicalls.py
unipacker/banner
unipacker/core.py
unipacker/fortunes
unipacker/headers.py
unipacker/imagedump.py
unipacker/io_handler.py
unipacker/kernel_structs.py
unipacker/malwrsig.yar
unipacker/packer_signatures.yar
unipacker/pe_structs.py
unipacker/shell.py
unipacker/unpackers.py
unipacker/utils.py
unipacker/DLLs/KernelBase.dll
unipacker/DLLs/KernelBase.ldll
unipacker/DLLs/kernel32.dll
unipacker/DLLs/kernel32.ldll
unipacker/DLLs/ntdll.dll
unipacker/DLLs/ntdll.ldll
unipacker-1.0.8.dist-info/LICENSE
unipacker-1.0.8.dist-info/METADATA
unipacker-1.0.8.dist-info/NOTICE
unipacker-1.0.8.dist-info/WHEEL
unipacker-1.0.8.dist-info/entry_points.txt
unipacker-1.0.8.dist-info/top_level.txt
unipacker-1.0.8.dist-info/RECORD
