Metadata-Version: 2.1
Name: unipacker
Version: 1.0.8
Summary: Automatic and platform-independent unpacker for Windows binaries based on emulation
Home-page: https://github.com/unipacker/unipacker
Author: Un{i}packer Team
Author-email: masrepus97@gmail.com
License: GPL-2.0
Requires-Python: >=3.10
License-File: LICENSE
License-File: NOTICE
Requires-Dist: yara-python
Requires-Dist: pefile
Requires-Dist: cmd2 ==2.0.0
Requires-Dist: unicorn-unipacker ==1.0.3b7
Requires-Dist: capstone
Requires-Dist: colorama
Requires-Dist: gnureadline ; platform_system == "Darwin"
Requires-Dist: pyreadline ; platform_system == "Windows"
